symphony_markdown/__init__.py
symphony_markdown/_frontend.py
symphony_markdown/_version.py
symphony_markdown/widget.py
symphony_markdown/labextension/build_log.json
symphony_markdown/labextension/package.json
symphony_markdown/labextension/static/lib_index_js.5836dfcc67ac6171217b.js
symphony_markdown/labextension/static/lib_index_js.5836dfcc67ac6171217b.js.map
symphony_markdown/labextension/static/lib_index_js.5b3126718cbba620e301.js
symphony_markdown/labextension/static/lib_index_js.5b3126718cbba620e301.js.map
symphony_markdown/labextension/static/remoteEntry.0023b58cdc7bf5c5e630.js
symphony_markdown/labextension/static/remoteEntry.0023b58cdc7bf5c5e630.js.map
symphony_markdown/labextension/static/remoteEntry.59482efe22fda69f2179.js
symphony_markdown/labextension/static/remoteEntry.59482efe22fda69f2179.js.map
symphony_markdown/labextension/static/style.js
symphony_markdown/nbextension/extension.js
symphony_markdown/nbextension/index.js
symphony_markdown/standalone/widgets/SymphonyMarkdown.js
symphony_markdown/standalone/widgets/SymphonyMarkdown.js.map
symphony_markdown-1.0.2.data/data/etc/jupyter/nbconfig/notebook.d/symphony_markdown.json
symphony_markdown-1.0.2.data/data/share/jupyter/labextensions/symphony-markdown/build_log.json
symphony_markdown-1.0.2.data/data/share/jupyter/labextensions/symphony-markdown/install.json
symphony_markdown-1.0.2.data/data/share/jupyter/labextensions/symphony-markdown/package.json
symphony_markdown-1.0.2.data/data/share/jupyter/labextensions/symphony-markdown/static/lib_index_js.5836dfcc67ac6171217b.js
symphony_markdown-1.0.2.data/data/share/jupyter/labextensions/symphony-markdown/static/lib_index_js.5836dfcc67ac6171217b.js.map
symphony_markdown-1.0.2.data/data/share/jupyter/labextensions/symphony-markdown/static/remoteEntry.0023b58cdc7bf5c5e630.js
symphony_markdown-1.0.2.data/data/share/jupyter/labextensions/symphony-markdown/static/remoteEntry.0023b58cdc7bf5c5e630.js.map
symphony_markdown-1.0.2.dist-info/LICENSE.txt
symphony_markdown-1.0.2.dist-info/METADATA
symphony_markdown-1.0.2.dist-info/WHEEL
symphony_markdown-1.0.2.dist-info/top_level.txt
symphony_markdown-1.0.2.dist-info/RECORD
